.DS_Store
Python_SDK/client.py
pyonic/__init__.py
pyonic/client.py
pyonic/Deliveries/__init__.py
pyonic/Deliveries/deliveries.py
pyonic-1.0.8.dist-info/LICENSE.txt
pyonic-1.0.8.dist-info/METADATA
pyonic-1.0.8.dist-info/WHEEL
pyonic-1.0.8.dist-info/top_level.txt
pyonic-1.0.8.dist-info/RECORD
