Metadata-Version: 2.1
Name: pyonic
Version: 1.0.8
Summary: A python SDK for the Ion-Channel application
Home-page: https://github.com/ion-channel/ion-channel-python-sdk
Author: Ion Channel
Author-email: dev@ionchannel.io
License: MIT
Platform: UNKNOWN
Classifier: License :: OSI Approved :: MIT License
Classifier: Programming Language :: Python :: 3
Classifier: Operating System :: OS Independent
Requires-Python: >=3.6
License-File: LICENSE.txt
Requires-Dist: requests
